MANIFEST.in
README.txt
setup.py
c2/__init__.py
c2.patch.corepermission.egg-info/PKG-INFO
c2.patch.corepermission.egg-info/SOURCES.txt
c2.patch.corepermission.egg-info/dependency_links.txt
c2.patch.corepermission.egg-info/entry_points.txt
c2.patch.corepermission.egg-info/namespace_packages.txt
c2.patch.corepermission.egg-info/not-zip-safe
c2.patch.corepermission.egg-info/requires.txt
c2.patch.corepermission.egg-info/top_level.txt
c2/patch/__init__.py
c2/patch/corepermission/__init__.py
c2/patch/corepermission/add_menu.py
c2/patch/corepermission/configure.zcml
c2/patch/corepermission/delete.py
c2/patch/corepermission/tests.py
c2/patch/corepermission/version.txt
docs/HISTORY.txt
docs/INSTALL.txt
docs/LICENSE.GPL
docs/LICENSE.txt