Metadata-Version: 1.1
Name: c2.patch.corepermission
Version: 1.0b1
Summary: This product is monkey patching for core permissions for Plone
Home-page: http://www.cmscom.jp
Author: Manabu TERADA
Author-email: terada@cmscom.jp
License: GPL
Keywords: plone patch permission
Platform: UNKNOWN
Classifier: Framework :: Plone
Classifier: Programming Language :: Python
